certbot_dns_gigahost/__init__.py
certbot_dns_gigahost/dns_gigahost.py
certbot_dns_gigahost/dns_gigahost_test.py
certbot_dns_gigahostdk-0.0.1.dist-info/LICENSE
certbot_dns_gigahostdk-0.0.1.dist-info/METADATA
certbot_dns_gigahostdk-0.0.1.dist-info/WHEEL
certbot_dns_gigahostdk-0.0.1.dist-info/entry_points.txt
certbot_dns_gigahostdk-0.0.1.dist-info/top_level.txt
certbot_dns_gigahostdk-0.0.1.dist-info/RECORD
